aafigure/PILhelper.py
aafigure/__init__.py
aafigure/__main__.py
aafigure/aa.py
aafigure/aafigure.py
aafigure/error.py
aafigure/pdf.py
aafigure/pil.py
aafigure/shapes.py
aafigure/sphinxext.py
aafigure/svg.py
aafigure-0.6.data/scripts/aafigure
aafigure-0.6.dist-info/DESCRIPTION.rst
aafigure-0.6.dist-info/METADATA
aafigure-0.6.dist-info/RECORD
aafigure-0.6.dist-info/WHEEL
aafigure-0.6.dist-info/metadata.json
aafigure-0.6.dist-info/top_level.txt
