Metadata-Version: 2.0
Name: aafigure
Version: 0.6
Summary: ASCII art to image converter
Home-page: http://launchpad.net/aafigure
Author: Chris Liechti
Author-email: cliechti@gmx.net
License: BSD
Platform: any
Classifier: Development Status :: 4 - Beta
Classifier: Environment :: Console
Classifier: Intended Audience :: Developers
Classifier: License :: OSI Approved :: BSD License
Classifier: Operating System :: OS Independent
Classifier: Programming Language :: Python
Classifier: Topic :: Documentation
Classifier: Topic :: Utilities
